crutil/__init__.py
crutil/c_utils.py
crutil/collatz.py
crutil/combinatorics.py
crutil/primes.py
crutil/rust_utils.py
crutil/utils.py
crutil/c/combinatorics/main.c
crutil/rust/hosker_collatz/Cargo.toml
crutil/rust/hosker_collatz/src/lib.rs
crutil/rust/hosker_primes/Cargo.toml
crutil/rust/hosker_primes/src/lib.rs
crutil-2.1.1.data/scripts/crutil-compile
crutil-2.1.1.data/scripts/crutil-install
crutil-2.1.1.dist-info/LICENSE
crutil-2.1.1.dist-info/METADATA
crutil-2.1.1.dist-info/WHEEL
crutil-2.1.1.dist-info/top_level.txt
crutil-2.1.1.dist-info/RECORD
